{"pageProps":{"preview":false,"data":{"movie":{"title":"Blade Runner 2049","poster":{"asset":{"_type":"reference","_ref":"image-c6683ff02881704e326ca8b198af122e18513570-780x1170-jpg"},"crop":{"left":0,"bottom":0.27594392523364486,"right":0,"top":0},"hotspot":{"width":0.5389408099688473,"x":0.5342679127725857,"y":0.16285046728971952,"height":0.16801869158878502},"_type":"image"},"overview":[{"children":[{"marks":[],"text":"Thirty years after the events of the first film, a new blade runner, LAPD Officer K, unearths a long-buried secret that has the potential to plunge what's left of society into chaos. K's discovery leads him on a quest to find Rick Deckard, a former LAPD blade runner who has been missing for 30 years.","_key":"KYwlUTD9","_type":"span"}],"_type":"block","style":"normal","_key":"b455f8b1974edb4c7f4a3aeefededec4","markDefs":[]}]},"queryParams":{}}},"__N_SSG":true}