{"pageProps":{"preview":false,"data":{"movie":{"title":"Guardians of the Galaxy","poster":{"_type":"image","asset":{"_type":"reference","_ref":"image-236a8e4d456db62a04f85c39abcfd74c50e0c37b-780x1170-jpg"},"crop":{"top":0,"left":0,"bottom":0.21992523364486016,"right":0},"hotspot":{"width":0.190031152647975,"x":0.5218068535825545,"y":0.22094392523364464,"height":0.10162616822429898}},"overview":[{"markDefs":[],"children":[{"_type":"span","marks":[],"text":"Light years from Earth, 26 years after being abducted, Peter Quill finds himself the prime target of a manhunt after discovering an orb wanted by Ronan the Accuser.","_key":"Ysh3M4E5"}],"_type":"block","style":"normal","_key":"b4832657f00653e44865d2cac5a62033"}]},"queryParams":{}}},"__N_SSG":true}